LICENSE
README.md
pyproject.toml
setup.py
chatarena/__init__.py
chatarena/agent.py
chatarena/arena.py
chatarena/arena_new.py
chatarena/arena_xl.py
chatarena/config.py
chatarena/database.py
chatarena/message.py
chatarena/pettingzoo_compatibility.py
chatarena/pgm.py
chatarena/utils.py
chatarena/backends/__init__.py
chatarena/backends/anthropic.py
chatarena/backends/bard.py
chatarena/backends/base.py
chatarena/backends/cohere.py
chatarena/backends/customized.py
chatarena/backends/hf_transformers.py
chatarena/backends/human.py
chatarena/backends/langchain.py
chatarena/backends/openai.py
chatarena/backends/openai_xl.py
chatarena/environments/__init__.py
chatarena/environments/base.py
chatarena/environments/chameleon.py
chatarena/environments/chameleon_competition.py
chatarena/environments/chameleon_competition_old.py
chatarena/environments/chameleon_competition_pgm.py
chatarena/environments/chameleon_competition_pgm_old.py
chatarena/environments/chameleon_competition_pgm_simple.py
chatarena/environments/chameleon_inter.py
chatarena/environments/chameleon_iter.py
chatarena/environments/chameleon_pgm.py
chatarena/environments/chameleon_pgm_cal.py
chatarena/environments/chameleon_pgm_cal_active.py
chatarena/environments/chameleon_pgm_cal_active_fewshot.py
chatarena/environments/chameleon_textpgm_noiter.py
chatarena/environments/conversation.py
chatarena/environments/pettingzoo_chess.py
chatarena/environments/pettingzoo_tictactoe.py
chatarena/environments/undercover_competition.py
chatarena/environments/undercover_competition_old.py
chatarena/environments/undercover_competition_pgm.py
chatarena/environments/undercover_competition_pgm_multi.py
chatarena/environments/undercover_competition_pgm_old.py
chatarena/environments/undercover_competition_pgm_old_v1.py
chatarena/environments/umshini/__init__.py
chatarena/environments/umshini/base.py
chatarena/environments/umshini/debate.py
chatarena/environments/umshini/pettingzoo_wrapper.py
llm_agent.egg-info/PKG-INFO
llm_agent.egg-info/SOURCES.txt
llm_agent.egg-info/dependency_links.txt
llm_agent.egg-info/requires.txt
llm_agent.egg-info/top_level.txt
