Metadata-Version: 2.1
Name: llm-agent
Version: 0.3.0
Summary: Multi-Agent Language Game Environments for Large Language Models
Home-page: https://github.com/chatarena/chatarena
Author: Zhiyuan Hu
Author-email: Zhiyuan Hu <zhiyuan.hu.bj@gmail.com>
License: UNKNOWN
Project-URL: Homepage, https://github.com/chatarena/chatarena
Project-URL: Bug Tracker, https://github.com/chatarena/chatarena/issues
Platform: UNKNOWN
Classifier: Programming Language :: Python :: 3
Classifier: License :: OSI Approved :: MIT License
Classifier: Operating System :: OS Independent
Requires-Python: >=3.7
Provides-Extra: all_backends
Provides-Extra: all
Provides-Extra: anthropic
Provides-Extra: cohere
Provides-Extra: huggingface
Provides-Extra: bard
Provides-Extra: langchain
Provides-Extra: gradio
Provides-Extra: pettingzoo
Provides-Extra: umshini
Provides-Extra: all_envs
License-File: LICENSE
